odoo10_addon_partner_contact_in_several_companies-10.0.1.0.0-py2.7-nspkg.pth
odoo10_addon_partner_contact_in_several_companies-10.0.1.0.0.dist-info/top_level.txt
odoo10_addon_partner_contact_in_several_companies-10.0.1.0.0.dist-info/WHEEL
odoo10_addon_partner_contact_in_several_companies-10.0.1.0.0.dist-info/RECORD
odoo10_addon_partner_contact_in_several_companies-10.0.1.0.0.dist-info/metadata.json
odoo10_addon_partner_contact_in_several_companies-10.0.1.0.0.dist-info/DESCRIPTION.rst
odoo10_addon_partner_contact_in_several_companies-10.0.1.0.0.dist-info/METADATA
odoo10_addon_partner_contact_in_several_companies-10.0.1.0.0.dist-info/namespace_packages.txt
odoo/addons/partner_contact_in_several_companies/__manifest__.py
odoo/addons/partner_contact_in_several_companies/__init__.py
odoo/addons/partner_contact_in_several_companies/README.rst
odoo/addons/partner_contact_in_several_companies/models/res_partner.py
odoo/addons/partner_contact_in_several_companies/models/__init__.py
odoo/addons/partner_contact_in_several_companies/models/ir_actions.py
odoo/addons/partner_contact_in_several_companies/i18n/partner_contact_in_several_companies.pot
odoo/addons/partner_contact_in_several_companies/i18n/it.po
odoo/addons/partner_contact_in_several_companies/i18n/es.po
odoo/addons/partner_contact_in_several_companies/i18n/sl.po
odoo/addons/partner_contact_in_several_companies/i18n/da.po
odoo/addons/partner_contact_in_several_companies/i18n/nl.po
odoo/addons/partner_contact_in_several_companies/i18n/de.po
odoo/addons/partner_contact_in_several_companies/i18n/fr.po
odoo/addons/partner_contact_in_several_companies/i18n/pt_BR.po
odoo/addons/partner_contact_in_several_companies/i18n/fi.po
odoo/addons/partner_contact_in_several_companies/i18n/hr_HR.po
odoo/addons/partner_contact_in_several_companies/views/res_partner.xml
odoo/addons/partner_contact_in_several_companies/tests/__init__.py
odoo/addons/partner_contact_in_several_companies/tests/test_partner_contact_in_several_companies.py
odoo/addons/partner_contact_in_several_companies/demo/ir_actions.xml
odoo/addons/partner_contact_in_several_companies/demo/res_partner.xml
odoo/addons/partner_contact_in_several_companies/static/description/icon.png
