Metadata-Version: 2.0
Name: odoo10-addon-partner-contact-in-several-companies
Version: 10.0.1.0.0
Summary: Allow to have one contact in several partners
Home-page: https://odoo-community.org/
Author: Odoo Community Association (OCA),Odoo SA
Author-email: support@odoo-community.org
License: AGPL-3
Platform: UNKNOWN
Requires-Dist: odoo (<10.1dev,>=10.0)
Requires-Dist: odoo10-addon-partner-contact-personal-information-page
Classifier: Programming Language :: Python :: 2.7
Classifier: Framework :: Odoo
Classifier: License :: OSI Approved :: GNU Affero General Public License v3
